README.md
setup.py
samples/__init__.py
samples/consumer.py
samples/producer.py
soybean/__init__.py
soybean/channel.py
soybean/exceptions.py
soybean/subscription.py
soybean/utils.py
soybean.egg-info/PKG-INFO
soybean.egg-info/SOURCES.txt
soybean.egg-info/dependency_links.txt
soybean.egg-info/not-zip-safe
soybean.egg-info/requires.txt
soybean.egg-info/top_level.txt
tests/__init__.py